pydiva/__init__.py
pydiva/farc_load_helper.py
pydiva/pyfarc.py
pydiva/pyfarc_formats.py
pydiva/pyfarc_ft_helpers.py
pydiva/pyfmh3.py
pydiva/pyfmh3_formats.py
pydiva/util/__init__.py
pydiva/util/cs3_file_utils.py
pydiva-1.1.1.dist-info/METADATA
pydiva-1.1.1.dist-info/WHEEL
pydiva-1.1.1.dist-info/top_level.txt
pydiva-1.1.1.dist-info/RECORD
