Metadata-Version: 2.1
Name: pydiva
Version: 1.1.1
Summary: Some stuff for handling files from Project DIVA games
Home-page: https://github.com/somewhatlurker/pydiva
Author: somewhatlurker
License: UNKNOWN
Platform: UNKNOWN
Classifier: Programming Language :: Python :: 3
Classifier: License :: OSI Approved :: MIT License
Classifier: Operating System :: OS Independent
Requires-Python: >=3.8
Requires-Dist: construct (>=2.9.0)
Requires-Dist: pycryptodomex
